{"@type":"Process","@id":"770e1fc3-5871-3668-9211-71c8e8983773","name":"market for transport, freight, aircraft, medium haul | transport, freight, aircraft, medium haul | Cutoff, U","description":"ecoQuery: https://ecoquery.ecoinvent.org/3.10/cutoff/dataset/21239/documentation\n\nThis is a market activity. Each market represents the consumption mix of a product in a given geography, connecting suppliers with consumers of the same product in the same geographical area. Markets group the producers and also the imports of the product (if relevant) within the same geographical area. They also account for transport to the consumer and for the losses during that process, when relevant.;This is the market for  \u0027transport, freight, aircraft, medium haul\u0027, in the Global geography.;This market contains no transport or losses, as they are irrelevant for the delivered product.;This is delivering the service of transportation of 1 metric ton across the distance of 1 km. This service only considers the transportation of goods. The vehicle operates with kerosene. Its operation is an average flight of a medium-haul aircraft for distance between 1500 km and 4000 km.   The transport node indirectly considers empty trips (if any) by taking into account the total amount of freight transported throughout the lifetime of the mobile infrastructure.\n\nThis activity starts with the service generation.\n\n\nThis activity ends with the service supplied to its consumers. Transport or losses are considered irrelevant for this product.","category":"H:Transportation and storage/51:Air transport/511:Passenger air transport/5110:Passenger air transport","version":"00.00.000","tags":["Sector: Transport"],"processType":"UNIT_PROCESS","isInfrastructureProcess":false,"location":{"@type":"Location","@id":"56bca136-90bb-3a77-9abb-7ce558af711e","name":"Global","category":"Global"},"processDocumentation":{"validFrom":"2016-01-01","validUntil":"2023-12-31","dataGenerator":{"@type":"Actor","@id":"c4597934-ecac-422c-b431-382e85fdcb83","name":"[System]"},"dataDocumentor":{"@type":"Actor","@id":"c4597934-ecac-422c-b431-382e85fdcb83","name":"[System]"},"creationDate":"2018-06-14T19:48:57Z","isCopyrightProtected":false},"lastInternalId":3,"exchangeDqSystem":{"@type":"DQSystem","@id":"e7ac7cf6-5457-453e-99f9-d889826fffe8","name":"ecoinvent Data Quality System"},"parameters":[],"exchanges":[{"@type":"Exchange","isAvoidedProduct":false,"isInput":false,"amount":1.0,"description":"","costValue":0.0437802442214359,"currency":{"@type":"Currency","@id":"7de74e65-ff97-404f-bf57-5d2a9134fb43","name":"Euro","refUnit":"EUR"},"internalId":1,"location":{"@type":"Location","@id":"56bca136-90bb-3a77-9abb-7ce558af711e","name":"Global","category":"Global"},"flow":{"@type":"Flow","@id":"220fe333-5329-4a8d-b012-1db429f2383b","name":"transport, freight, aircraft, medium haul","category":"H:Transportation and storage/51:Air transport/511:Passenger air transport/5110:Passenger air transport","flowType":"PRODUCT_FLOW","refUnit":"t*km"},"unit":{"@type":"Unit","@id":"0dea4ed8-bb6b-4049-b2b4-b2c413ef2180","name":"t*km"},"flowProperty":{"@type":"FlowProperty","@id":"838aaa20-0117-11db-92e3-0800200c9a66","name":"Mass transport","category":"Technical flow properties","refUnit":"t*km"},"isQuantitativeReference":true},{"@type":"Exchange","isAvoidedProduct":false,"isInput":true,"amount":0.248175182481752,"description":"","costValue":0.0108651700987505,"currency":{"@type":"Currency","@id":"7de74e65-ff97-404f-bf57-5d2a9134fb43","name":"Euro","refUnit":"EUR"},"internalId":2,"location":{"@type":"Location","@id":"56bca136-90bb-3a77-9abb-7ce558af711e","name":"Global","category":"Global"},"flow":{"@type":"Flow","@id":"220fe333-5329-4a8d-b012-1db429f2383b","name":"transport, freight, aircraft, medium haul","category":"H:Transportation and storage/51:Air transport/511:Passenger air transport/5110:Passenger air transport","flowType":"PRODUCT_FLOW","refUnit":"t*km"},"unit":{"@type":"Unit","@id":"0dea4ed8-bb6b-4049-b2b4-b2c413ef2180","name":"t*km"},"flowProperty":{"@type":"FlowProperty","@id":"838aaa20-0117-11db-92e3-0800200c9a66","name":"Mass transport","category":"Technical flow properties","refUnit":"t*km"},"defaultProvider":{"@type":"Process","@id":"e4921aab-295c-310f-864b-6fffbba7a295","name":"transport, freight, aircraft, dedicated freight, medium haul | transport, freight, aircraft, medium haul | Cutoff, U","category":"H:Transportation and storage/51:Air transport/511:Passenger air transport/5110:Passenger air transport","processType":"UNIT_PROCESS","flowType":"PRODUCT_FLOW","location":"GLO"}},{"@type":"Exchange","isAvoidedProduct":false,"isInput":true,"amount":0.751824817518248,"description":"","costValue":0.0329150741226853,"currency":{"@type":"Currency","@id":"7de74e65-ff97-404f-bf57-5d2a9134fb43","name":"Euro","refUnit":"EUR"},"internalId":3,"location":{"@type":"Location","@id":"56bca136-90bb-3a77-9abb-7ce558af711e","name":"Global","category":"Global"},"flow":{"@type":"Flow","@id":"220fe333-5329-4a8d-b012-1db429f2383b","name":"transport, freight, aircraft, medium haul","category":"H:Transportation and storage/51:Air transport/511:Passenger air transport/5110:Passenger air transport","flowType":"PRODUCT_FLOW","refUnit":"t*km"},"unit":{"@type":"Unit","@id":"0dea4ed8-bb6b-4049-b2b4-b2c413ef2180","name":"t*km"},"flowProperty":{"@type":"FlowProperty","@id":"838aaa20-0117-11db-92e3-0800200c9a66","name":"Mass transport","category":"Technical flow properties","refUnit":"t*km"},"defaultProvider":{"@type":"Process","@id":"2cf59ff5-efec-34a6-9699-ed96ef91eedf","name":"transport, freight, aircraft, belly-freight, medium haul | transport, freight, aircraft, medium haul | Cutoff, U","category":"H:Transportation and storage/51:Air transport/511:Passenger air transport/5110:Passenger air transport","processType":"UNIT_PROCESS","flowType":"PRODUCT_FLOW","location":"GLO"}}],"socialAspects":[],"allocationFactors":[]}