{"@type":"Process","@id":"a03a5ce2-4c41-3d84-bd7d-902294d5b898","name":"market for hard coal | hard coal | Cutoff, U","description":"ecoQuery: https://ecoquery.ecoinvent.org/3.10/cutoff/dataset/7102/documentation\n\nThis is a market activity. Each market represents the consumption mix of a product in a given geography, connecting suppliers with consumers of the same product in the same geographical area. Markets group the producers and also the imports of the product (if relevant) within the same geographical area. They also account for transport to the consumer and for the losses during that process, when relevant.;This is the market for  \u0027hard coal\u0027, in the geography of Russia.;This dataset covers the average transport distance specific to the domestic market of hard coal in Russia. Russia holds the world’s third-largest recoverable coal reserves (after the US and China) and was the sixth-largest coal producer in 2016. About 80% of the country’s production is steam coal, about 20% coking coal. The main mining area is located in the Kuzbass basin in Central Russia. About 45% of coal is consumed domestically, the rest is exported to Europe and Asia. Domestic consumers, mostly power plants are located both in direct vicinity to the mines as well as in the far east and west of the country. Long-distance transport typically ranges between 800-2000km (Walker, 2000), while power plants at the mines hardly require transport. We therefore estimate the average distance at the lower end of the long-distance range, namely 800km. Due to the long transport distances coal in Russia is commonly transported via rail. Average distances to the major exporting ports is estimated to be at the higher end of the long-distance range, namely 2000km. (The balance between 800km and 2000km is required by export coal only and thus covered in the “hard coal, import from RU” datasets.) The main ports for coal are: Murmansk, Ust-Luga, and Tuapse in the West for exports to Europe; Vanino and Vostochny in the East to handle exports to Asia (IEA, 2017).;Dust from transport and load/unload operations is included. Average coal losses are considered. Average emissions to water due to leaching from coal heaps at storage is estimated from the literature.;Reference(s): IEA. 2017. Country Analysis Brief: Russia. Accessed online at: https://www.eia.gov/beta/international/analysis_includes/countries_long/Russia/russia.pdf,;Walker, S., 2000. Major coalfields of the world. ISBN: 929029342X 9789290293422.;;hard coal\u0027 is a fossil fuel with a calorific value of 27.91 MJ/kg. It is used as a solid fuel and is sourced from coal mines after crushing, screening and washing the coal. Its main applications are in the following sectors: domestic fuel (mainly for hand-fired stoves), as filter media and as an ingredient in charcoal briquettes.\n\nThis activity starts at the hard coal preparation plant with the beneficiated coal ready to be loaded on rail, truck, barge or conveyor.\n\nactivity end: The activity ends with the unloading of hard coal at domestic consumers or export hubs. Losses are included.","category":"B:Mining and quarrying/05:Mining of coal and lignite/051:Mining of hard coal/0510:Mining of hard coal","version":"00.00.000","tags":["Sector: Fuels"],"processType":"UNIT_PROCESS","isInfrastructureProcess":false,"location":{"@type":"Location","@id":"89484b14-b36a-3d53-a942-6a3d944d2983","name":"Russia","category":"Country"},"processDocumentation":{"validFrom":"2014-01-01","validUntil":"2023-12-31","geographyDescription":"Transport distances are geography specific, losses and related emissions are generic values applicable worldwide.","technologyDescription":"Not specified","dataTreatmentDescription":"Transport data geography specific, emissions, losses, energy and land requirements are generic assumptions.","samplingDescription":"literature","dataGenerator":{"@type":"Actor","@id":"ab2a5a32-7e0d-431a-9f6c-9011ff140de7","name":"Florentine Brunner"},"dataDocumentor":{"@type":"Actor","@id":"ab2a5a32-7e0d-431a-9f6c-9011ff140de7","name":"Florentine Brunner"},"creationDate":"2017-11-21T20:31:50Z","publication":{"@type":"Source","@id":"6ad10bdb-b629-4991-94a9-478b752cde90","name":"Röder, A.2007"},"isCopyrightProtected":true},"lastInternalId":28,"exchangeDqSystem":{"@type":"DQSystem","@id":"e7ac7cf6-5457-453e-99f9-d889826fffe8","name":"ecoinvent Data Quality System"},"parameters":[],"exchanges":[{"@type":"Exchange","isAvoidedProduct":false,"isInput":false,"amount":1.0,"description":"EcoSpold01Location\u003dWEU","costValue":0.036,"currency":{"@type":"Currency","@id":"7de74e65-ff97-404f-bf57-5d2a9134fb43","name":"Euro","refUnit":"EUR"},"internalId":1,"location":{"@type":"Location","@id":"89484b14-b36a-3d53-a942-6a3d944d2983","name":"Russia","category":"Country"},"flow":{"@type":"Flow","@id":"0d3eda5a-4601-4573-9549-0701c459ab88","name":"hard coal","category":"B:Mining and quarrying/05:Mining of coal and lignite/051:Mining of hard coal/0510:Mining of hard coal","flowType":"PRODUCT_FLOW","refUnit":"kg"},"unit":{"@type":"Unit","@id":"95dd50e9-c184-4412-9afc-9764b1ffcf8f","name":"kg SWU"},"flowProperty":{"@type":"FlowProperty","@id":"93a60a56-a3c8-11da-a746-0800200b9a66","name":"Mass","category":"Technical flow properties","refUnit":"kg"},"isQuantitativeReference":true},{"@type":"Exchange","isAvoidedProduct":false,"isInput":true,"amount":0.11152947454063625,"dqEntry":"(1;1;4;5;4)","description":"The main mining area is located in the Kuzbass basin in Central Russia. About 45% of coal is consumed domestically, the rest is exported to Europe and Asia. Domestic consumers, mostly power plants are located both in direct vicinity to the mines as well as in the far east and west of the country. Long-distance transport typically ranges between 800-2000km (Walker, 2000), while power plants at the mines hardly require transport. We therefore estimate the average distance at the lower end of the long-distance range, namely 800km. Due to the long transport distances coal in Russia is commonly transported via rail. Average distances to the major exporting ports is estimated to be at the higher end of the long-distance range, namely 2000km. (The balance between 800km and 2000km is required by export coal only and thus covered in the “hard coal, import from RU” datasets.) The main ports for coal are: Murmansk, Ust-Luga, and Tuapse in the West for exports to Europe; Vanino and Vostochny in the East to handle exports to Asia (IEA, 2017).\nDust from transport and load/unload operations is included. Average coal losses are considered. Average emissions to water due to leaching from coal heaps at storage is estimated from the literature.\nReference(s): IEA. 2017. Country Analysis Brief: Russia. Accessed online at: \u003chttps://www.eia.gov/beta/international/analysis_includes/countries_long/Russia/russia.pdf\u003e,\nWalker, S., 2000. Major coalfields of the world. ISBN: 929029342X 9789290293422.\n","costValue":0.00289976633805654,"currency":{"@type":"Currency","@id":"7de74e65-ff97-404f-bf57-5d2a9134fb43","name":"Euro","refUnit":"EUR"},"internalId":5,"location":{"@type":"Location","@id":"817ed804-f0ed-3175-b39d-7576a1c242b1","name":"Europe without Switzerland","category":"Custom"},"flow":{"@type":"Flow","@id":"0ace02fa-eca5-482d-a829-c18e46a52db4","name":"transport, freight train","category":"H:Transportation and storage/49:Land transport and transport via pipelines/491:Transport via railways/4912:Freight rail transport","flowType":"PRODUCT_FLOW","refUnit":"t*km"},"unit":{"@type":"Unit","@id":"0dea4ed8-bb6b-4049-b2b4-b2c413ef2180","name":"t*km"},"flowProperty":{"@type":"FlowProperty","@id":"838aaa20-0117-11db-92e3-0800200c9a66","name":"Mass transport","category":"Technical flow properties","refUnit":"t*km"},"uncertainty":{"@type":"Uncertainty","distributionType":"LOG_NORMAL_DISTRIBUTION","geomMean":0.11152947454063625,"geomSd":1.4139824580805163},"defaultProvider":{"@type":"Process","@id":"5092c31d-07a0-38f5-96ac-cc63d4a9de16","name":"market for transport, freight train | transport, freight train | Cutoff, U","category":"H:Transportation and storage/49:Land transport and transport via pipelines/491:Transport via railways/4912:Freight rail transport","processType":"UNIT_PROCESS","flowType":"PRODUCT_FLOW","location":"Europe without Switzerland"}},{"@type":"Exchange","isAvoidedProduct":false,"isInput":true,"amount":1.0E-5,"dqEntry":"(1;1;2;1;1)","description":"Assumption by Dones et al.: per one time of unloading from transport mode, (storing) and loading on subsequent transport mode an average demand (electric) energy of 7.2 kWh/tonne and an average land use demand of 1m2*a/tonne is required.\nReference(s):\nDones, R., Bauer, C., Röder, A. (2007) Kohle. In: Dones, R. (Ed.) et al., Sachbilanzen von Energiesystemen: Grundlagen für den ökologischen Vergleich von Energiesystemen und den Einbezug von Energiesystemen in Ökobilanzen für die Schweiz. Final report ecoinvent No. 6-VI, Paul Scherrer Institut Villigen, Swiss Centre for Life Cycle Inventories, Dübendorf, CH.","internalId":27,"location":{"@type":"Location","@id":"89484b14-b36a-3d53-a942-6a3d944d2983","name":"Russia","category":"Country"},"flow":{"@type":"Flow","@id":"29630a65-f38c-48a5-9744-c0121f586640","name":"Transformation, from unspecified","category":"Elementary flows/Resource/land","flowType":"ELEMENTARY_FLOW","refUnit":"m2"},"unit":{"@type":"Unit","@id":"3ce61faa-5716-41c1-aef6-b5920054acc9","name":"m2"},"flowProperty":{"@type":"FlowProperty","@id":"93a60a56-a3c8-19da-a746-0800200c9a66","name":"Area","category":"Technical flow properties","refUnit":"m2"},"uncertainty":{"@type":"Uncertainty","distributionType":"LOG_NORMAL_DISTRIBUTION","geomMean":1.0E-5,"geomSd":1.729310125349922}},{"@type":"Exchange","isAvoidedProduct":false,"isInput":false,"amount":2.0E-10,"dqEntry":"(1;1;2;1;1)","description":"Assumption by Dones, R., Bauer, C., Röder, A. (2007) Kohle. In: Dones, R. (Ed.) et al., Sachbilanzen von Energiesystemen: Grundlagen für den ökologischen Vergleich von Energiesystemen und den Einbezug von Energiesystemen in Ökobilanzen für die Schweiz. Final report ecoinvent No. 6-VI, Paul Scherrer Institut Villigen, Swiss Centre for Life Cycle Inventories, Dübendorf, CH.","internalId":25,"location":{"@type":"Location","@id":"89484b14-b36a-3d53-a942-6a3d944d2983","name":"Russia","category":"Country"},"flow":{"@type":"Flow","@id":"f73177d8-5e57-4f0d-ba34-6889cfdfed40","name":"Tin ion","category":"Elementary flows/Emission to water/ground water","flowType":"ELEMENTARY_FLOW","refUnit":"kg"},"unit":{"@type":"Unit","@id":"95dd50e9-c184-4412-9afc-9764b1ffcf8f","name":"kg SWU"},"flowProperty":{"@type":"FlowProperty","@id":"93a60a56-a3c8-11da-a746-0800200b9a66","name":"Mass","category":"Technical flow properties","refUnit":"kg"},"uncertainty":{"@type":"Uncertainty","distributionType":"LOG_NORMAL_DISTRIBUTION","geomMean":2.0E-10,"geomSd":3.168493566955497}},{"@type":"Exchange","isAvoidedProduct":false,"isInput":false,"amount":3.7037037037037E-8,"dqEntry":"(1;1;2;1;1)","description":"Calculated as equal to TOC.","internalId":15,"location":{"@type":"Location","@id":"89484b14-b36a-3d53-a942-6a3d944d2983","name":"Russia","category":"Country"},"flow":{"@type":"Flow","@id":"73eed463-4986-4d81-8bae-60dae5be49d0","name":"DOC, Dissolved Organic Carbon","category":"Elementary flows/Emission to water/ground water","flowType":"ELEMENTARY_FLOW","refUnit":"kg"},"unit":{"@type":"Unit","@id":"95dd50e9-c184-4412-9afc-9764b1ffcf8f","name":"kg SWU"},"flowProperty":{"@type":"FlowProperty","@id":"93a60a56-a3c8-11da-a746-0800200b9a66","name":"Mass","category":"Technical flow properties","refUnit":"kg"},"uncertainty":{"@type":"Uncertainty","distributionType":"LOG_NORMAL_DISTRIBUTION","geomMean":3.7037037037037E-8,"geomSd":1.729310125349922}},{"@type":"Exchange","isAvoidedProduct":false,"isInput":false,"amount":4.0E-5,"dqEntry":"(1;1;2;1;1)","description":"Assumption by Dones, R., Bauer, C., Röder, A. (2007) Kohle. In: Dones, R. (Ed.) et al., Sachbilanzen von Energiesystemen: Grundlagen für den ökologischen Vergleich von Energiesystemen und den Einbezug von Energiesystemen in Ökobilanzen für die Schweiz. Final report ecoinvent No. 6-VI, Paul Scherrer Institut Villigen, Swiss Centre for Life Cycle Inventories, Dübendorf, CH.","internalId":23,"location":{"@type":"Location","@id":"89484b14-b36a-3d53-a942-6a3d944d2983","name":"Russia","category":"Country"},"flow":{"@type":"Flow","@id":"31eacbfc-683a-4d36-afc1-80dee42a3b94","name":"Sulfate","category":"Elementary flows/Emission to water/ground water","flowType":"ELEMENTARY_FLOW","refUnit":"kg"},"unit":{"@type":"Unit","@id":"95dd50e9-c184-4412-9afc-9764b1ffcf8f","name":"kg SWU"},"flowProperty":{"@type":"FlowProperty","@id":"93a60a56-a3c8-11da-a746-0800200b9a66","name":"Mass","category":"Technical flow properties","refUnit":"kg"},"uncertainty":{"@type":"Uncertainty","distributionType":"LOG_NORMAL_DISTRIBUTION","geomMean":4.0E-5,"geomSd":2.239439866122061}},{"@type":"Exchange","isAvoidedProduct":false,"isInput":false,"amount":2.0E-6,"dqEntry":"(1;1;2;1;1)","description":"Assumption by Dones, R., Bauer, C., Röder, A. (2007) Kohle. In: Dones, R. (Ed.) et al., Sachbilanzen von Energiesystemen: Grundlagen für den ökologischen Vergleich von Energiesystemen und den Einbezug von Energiesystemen in Ökobilanzen für die Schweiz. Final report ecoinvent No. 6-VI, Paul Scherrer Institut Villigen, Swiss Centre for Life Cycle Inventories, Dübendorf, CH.","internalId":12,"location":{"@type":"Location","@id":"89484b14-b36a-3d53-a942-6a3d944d2983","name":"Russia","category":"Country"},"flow":{"@type":"Flow","@id":"85bec19f-c785-4364-8ef6-472b8e9dd90e","name":"Chloride","category":"Elementary flows/Emission to water/ground water","flowType":"ELEMENTARY_FLOW","refUnit":"kg"},"unit":{"@type":"Unit","@id":"95dd50e9-c184-4412-9afc-9764b1ffcf8f","name":"kg SWU"},"flowProperty":{"@type":"FlowProperty","@id":"93a60a56-a3c8-11da-a746-0800200b9a66","name":"Mass","category":"Technical flow properties","refUnit":"kg"},"uncertainty":{"@type":"Uncertainty","distributionType":"LOG_NORMAL_DISTRIBUTION","geomMean":2.0E-6,"geomSd":2.239439866122061}},{"@type":"Exchange","isAvoidedProduct":false,"isInput":true,"amount":0.001,"dqEntry":"(1;1;2;1;1)","description":"Assumption by Dones et al.: per one time of unloading from transport mode, (storing) and loading on subsequent transport mode an average demand (electric) energy of 7.2 kWh/tonne and an average land use demand of 1m2*a/tonne is required.\nReference(s):\nDones, R., Bauer, C., Röder, A. (2007) Kohle. In: Dones, R. (Ed.) et al., Sachbilanzen von Energiesystemen: Grundlagen für den ökologischen Vergleich von Energiesystemen und den Einbezug von Energiesystemen in Ökobilanzen für die Schweiz. Final report ecoinvent No. 6-VI, Paul Scherrer Institut Villigen, Swiss Centre for Life Cycle Inventories, Dübendorf, CH.","internalId":26,"location":{"@type":"Location","@id":"89484b14-b36a-3d53-a942-6a3d944d2983","name":"Russia","category":"Country"},"flow":{"@type":"Flow","@id":"fe9c3a98-a6d2-452d-a9a4-a13e64f1b95b","name":"Occupation, industrial area","category":"Elementary flows/Resource/land","flowType":"ELEMENTARY_FLOW","refUnit":"m2*a"},"unit":{"@type":"Unit","@id":"c7266b67-4ea2-457f-b391-9b94e26e195a","name":"m2*a"},"flowProperty":{"@type":"FlowProperty","@id":"93a60a56-a3c8-21da-a746-0800200c9a66","name":"Area*Time","category":"Technical flow properties","refUnit":"m2*a"},"uncertainty":{"@type":"Uncertainty","distributionType":"LOG_NORMAL_DISTRIBUTION","geomMean":0.001,"geomSd":1.729310125349922}},{"@type":"Exchange","isAvoidedProduct":false,"isInput":true,"amount":1.0,"description":"","costValue":0.036,"currency":{"@type":"Currency","@id":"7de74e65-ff97-404f-bf57-5d2a9134fb43","name":"Euro","refUnit":"EUR"},"internalId":4,"location":{"@type":"Location","@id":"89484b14-b36a-3d53-a942-6a3d944d2983","name":"Russia","category":"Country"},"flow":{"@type":"Flow","@id":"0d3eda5a-4601-4573-9549-0701c459ab88","name":"hard coal","category":"B:Mining and quarrying/05:Mining of coal and lignite/051:Mining of hard coal/0510:Mining of hard coal","flowType":"PRODUCT_FLOW","refUnit":"kg"},"unit":{"@type":"Unit","@id":"95dd50e9-c184-4412-9afc-9764b1ffcf8f","name":"kg SWU"},"flowProperty":{"@type":"FlowProperty","@id":"93a60a56-a3c8-11da-a746-0800200b9a66","name":"Mass","category":"Technical flow properties","refUnit":"kg"},"defaultProvider":{"@type":"Process","@id":"5467e0a6-a01b-39df-a93f-a11df0c07066","name":"hard coal mine operation and hard coal preparation | hard coal | Cutoff, U","category":"B:Mining and quarrying/05:Mining of coal and lignite/051:Mining of hard coal/0510:Mining of hard coal","processType":"UNIT_PROCESS","flowType":"PRODUCT_FLOW","location":"RU"}},{"@type":"Exchange","isAvoidedProduct":false,"isInput":true,"amount":0.6884705254593637,"dqEntry":"(1;1;4;5;4)","description":"The main mining area is located in the Kuzbass basin in Central Russia. About 45% of coal is consumed domestically, the rest is exported to Europe and Asia. Domestic consumers, mostly power plants are located both in direct vicinity to the mines as well as in the far east and west of the country. Long-distance transport typically ranges between 800-2000km (Walker, 2000), while power plants at the mines hardly require transport. We therefore estimate the average distance at the lower end of the long-distance range, namely 800km. Due to the long transport distances coal in Russia is commonly transported via rail. Average distances to the major exporting ports is estimated to be at the higher end of the long-distance range, namely 2000km. (The balance between 800km and 2000km is required by export coal only and thus covered in the “hard coal, import from RU” datasets.) The main ports for coal are: Murmansk, Ust-Luga, and Tuapse in the West for exports to Europe; Vanino and Vostochny in the East to handle exports to Asia (IEA, 2017).\nDust from transport and load/unload operations is included. Average coal losses are considered. Average emissions to water due to leaching from coal heaps at storage is estimated from the literature.\nReference(s): IEA. 2017. Country Analysis Brief: Russia. Accessed online at: \u003chttps://www.eia.gov/beta/international/analysis_includes/countries_long/Russia/russia.pdf\u003e,\nWalker, S., 2000. Major coalfields of the world. ISBN: 929029342X 9789290293422.\n","costValue":0.0179002336619434,"currency":{"@type":"Currency","@id":"7de74e65-ff97-404f-bf57-5d2a9134fb43","name":"Euro","refUnit":"EUR"},"internalId":6,"location":{"@type":"Location","@id":"f1965a85-7bc2-35d2-afe2-2023aa5ab50d","name":"Rest-of-World","category":"Custom"},"flow":{"@type":"Flow","@id":"0ace02fa-eca5-482d-a829-c18e46a52db4","name":"transport, freight train","category":"H:Transportation and storage/49:Land transport and transport via pipelines/491:Transport via railways/4912:Freight rail transport","flowType":"PRODUCT_FLOW","refUnit":"t*km"},"unit":{"@type":"Unit","@id":"0dea4ed8-bb6b-4049-b2b4-b2c413ef2180","name":"t*km"},"flowProperty":{"@type":"FlowProperty","@id":"838aaa20-0117-11db-92e3-0800200c9a66","name":"Mass transport","category":"Technical flow properties","refUnit":"t*km"},"uncertainty":{"@type":"Uncertainty","distributionType":"LOG_NORMAL_DISTRIBUTION","geomMean":0.6884705254593637,"geomSd":1.4139824580805163},"defaultProvider":{"@type":"Process","@id":"3db0e2e5-6111-3e33-ae90-e336d610535b","name":"market for transport, freight train | transport, freight train | Cutoff, U","category":"H:Transportation and storage/49:Land transport and transport via pipelines/491:Transport via railways/4912:Freight rail transport","processType":"UNIT_PROCESS","flowType":"PRODUCT_FLOW","location":"RoW"}},{"@type":"Exchange","isAvoidedProduct":false,"isInput":false,"amount":1.0E-7,"dqEntry":"(1;1;2;1;1)","description":"Assumption by Dones, R., Bauer, C., Röder, A. (2007) Kohle. In: Dones, R. (Ed.) et al., Sachbilanzen von Energiesystemen: Grundlagen für den ökologischen Vergleich von Energiesystemen und den Einbezug von Energiesystemen in Ökobilanzen für die Schweiz. Final report ecoinvent No. 6-VI, Paul Scherrer Institut Villigen, Swiss Centre for Life Cycle Inventories, Dübendorf, CH.","internalId":9,"location":{"@type":"Location","@id":"89484b14-b36a-3d53-a942-6a3d944d2983","name":"Russia","category":"Country"},"flow":{"@type":"Flow","@id":"57c27ba7-a61a-4932-8cd5-095c88ff0245","name":"BOD5, Biological Oxygen Demand","category":"Elementary flows/Emission to water/ground water","flowType":"ELEMENTARY_FLOW","refUnit":"kg"},"unit":{"@type":"Unit","@id":"95dd50e9-c184-4412-9afc-9764b1ffcf8f","name":"kg SWU"},"flowProperty":{"@type":"FlowProperty","@id":"93a60a56-a3c8-11da-a746-0800200b9a66","name":"Mass","category":"Technical flow properties","refUnit":"kg"},"uncertainty":{"@type":"Uncertainty","distributionType":"LOG_NORMAL_DISTRIBUTION","geomMean":1.0E-7,"geomSd":1.729310125349922}},{"@type":"Exchange","isAvoidedProduct":false,"isInput":false,"amount":4.0E-10,"dqEntry":"(1;1;2;1;1)","description":"Assumption by Dones, R., Bauer, C., Röder, A. (2007) Kohle. In: Dones, R. (Ed.) et al., Sachbilanzen von Energiesystemen: Grundlagen für den ökologischen Vergleich von Energiesystemen und den Einbezug von Energiesystemen in Ökobilanzen für die Schweiz. Final report ecoinvent No. 6-VI, Paul Scherrer Institut Villigen, Swiss Centre for Life Cycle Inventories, Dübendorf, CH.","internalId":20,"location":{"@type":"Location","@id":"89484b14-b36a-3d53-a942-6a3d944d2983","name":"Russia","category":"Country"},"flow":{"@type":"Flow","@id":"e030108f-2125-4bcb-a73b-ad72130fcca3","name":"Nickel II","category":"Elementary flows/Emission to water/ground water","flowType":"ELEMENTARY_FLOW","refUnit":"kg"},"unit":{"@type":"Unit","@id":"95dd50e9-c184-4412-9afc-9764b1ffcf8f","name":"kg SWU"},"flowProperty":{"@type":"FlowProperty","@id":"93a60a56-a3c8-11da-a746-0800200b9a66","name":"Mass","category":"Technical flow properties","refUnit":"kg"},"uncertainty":{"@type":"Uncertainty","distributionType":"LOG_NORMAL_DISTRIBUTION","geomMean":4.0E-10,"geomSd":3.168493566955497}},{"@type":"Exchange","isAvoidedProduct":false,"isInput":true,"amount":0.00215220425,"description":"","costValue":7.7479353E-5,"currency":{"@type":"Currency","@id":"7de74e65-ff97-404f-bf57-5d2a9134fb43","name":"Euro","refUnit":"EUR"},"internalId":3,"location":{"@type":"Location","@id":"89484b14-b36a-3d53-a942-6a3d944d2983","name":"Russia","category":"Country"},"flow":{"@type":"Flow","@id":"0d3eda5a-4601-4573-9549-0701c459ab88","name":"hard coal","category":"B:Mining and quarrying/05:Mining of coal and lignite/051:Mining of hard coal/0510:Mining of hard coal","flowType":"PRODUCT_FLOW","refUnit":"kg"},"unit":{"@type":"Unit","@id":"95dd50e9-c184-4412-9afc-9764b1ffcf8f","name":"kg SWU"},"flowProperty":{"@type":"FlowProperty","@id":"93a60a56-a3c8-11da-a746-0800200b9a66","name":"Mass","category":"Technical flow properties","refUnit":"kg"},"defaultProvider":{"@type":"Process","@id":"a03a5ce2-4c41-3d84-bd7d-902294d5b898","name":"market for hard coal | hard coal | Cutoff, U","category":"B:Mining and quarrying/05:Mining of coal and lignite/051:Mining of hard coal/0510:Mining of hard coal","processType":"UNIT_PROCESS","flowType":"PRODUCT_FLOW","location":"RU"}},{"@type":"Exchange","isAvoidedProduct":false,"isInput":false,"amount":1.0E-7,"dqEntry":"(1;1;2;1;1)","description":"Assumption by Dones, R., Bauer, C., Röder, A. (2007) Kohle. In: Dones, R. (Ed.) et al., Sachbilanzen von Energiesystemen: Grundlagen für den ökologischen Vergleich von Energiesystemen und den Einbezug von Energiesystemen in Ökobilanzen für die Schweiz. Final report ecoinvent No. 6-VI, Paul Scherrer Institut Villigen, Swiss Centre for Life Cycle Inventories, Dübendorf, CH.","internalId":10,"location":{"@type":"Location","@id":"89484b14-b36a-3d53-a942-6a3d944d2983","name":"Russia","category":"Country"},"flow":{"@type":"Flow","@id":"be10dd54-eb4d-48ae-9e14-7d79ce8b170d","name":"COD, Chemical Oxygen Demand","category":"Elementary flows/Emission to water/ground water","flowType":"ELEMENTARY_FLOW","refUnit":"kg"},"unit":{"@type":"Unit","@id":"95dd50e9-c184-4412-9afc-9764b1ffcf8f","name":"kg SWU"},"flowProperty":{"@type":"FlowProperty","@id":"93a60a56-a3c8-11da-a746-0800200b9a66","name":"Mass","category":"Technical flow properties","refUnit":"kg"},"uncertainty":{"@type":"Uncertainty","distributionType":"LOG_NORMAL_DISTRIBUTION","geomMean":1.0E-7,"geomSd":1.729310125349922}},{"@type":"Exchange","isAvoidedProduct":false,"isInput":false,"amount":0.002,"dqEntry":"(1;1;2;1;1)","description":"Assumption by Dones, R., Bauer, C., Röder, A. (2007) Kohle. In: Dones, R. (Ed.) et al., Sachbilanzen von Energiesystemen: Grundlagen für den ökologischen Vergleich von Energiesystemen und den Einbezug von Energiesystemen in Ökobilanzen für die Schweiz. Final report ecoinvent No. 6-VI, Paul Scherrer Institut Villigen, Swiss Centre for Life Cycle Inventories, Dübendorf, CH.","internalId":7,"location":{"@type":"Location","@id":"89484b14-b36a-3d53-a942-6a3d944d2983","name":"Russia","category":"Country"},"flow":{"@type":"Flow","@id":"7678cec7-b8e1-439d-8242-99cd452834b1","name":"Particulate Matter, \u003e 10 um","category":"Elementary flows/Emission to air/low population density","flowType":"ELEMENTARY_FLOW","refUnit":"kg"},"unit":{"@type":"Unit","@id":"95dd50e9-c184-4412-9afc-9764b1ffcf8f","name":"kg SWU"},"flowProperty":{"@type":"FlowProperty","@id":"93a60a56-a3c8-11da-a746-0800200b9a66","name":"Mass","category":"Technical flow properties","refUnit":"kg"},"uncertainty":{"@type":"Uncertainty","distributionType":"LOG_NORMAL_DISTRIBUTION","geomMean":0.002,"geomSd":3.168493566955497}},{"@type":"Exchange","isAvoidedProduct":false,"isInput":true,"amount":1.0E-5,"dqEntry":"(1;1;2;1;1)","description":"Assumption by Dones et al.: per one time of unloading from transport mode, (storing) and loading on subsequent transport mode an average demand (electric) energy of 7.2 kWh/tonne and an average land use demand of 1m2*a/tonne is required.\nReference(s):\nDones, R., Bauer, C., Röder, A. (2007) Kohle. In: Dones, R. (Ed.) et al., Sachbilanzen von Energiesystemen: Grundlagen für den ökologischen Vergleich von Energiesystemen und den Einbezug von Energiesystemen in Ökobilanzen für die Schweiz. Final report ecoinvent No. 6-VI, Paul Scherrer Institut Villigen, Swiss Centre for Life Cycle Inventories, Dübendorf, CH.\n","internalId":28,"location":{"@type":"Location","@id":"89484b14-b36a-3d53-a942-6a3d944d2983","name":"Russia","category":"Country"},"flow":{"@type":"Flow","@id":"4624deff-2016-41d4-b2bf-3db8dab88779","name":"Transformation, to industrial area","category":"Elementary flows/Resource/land","flowType":"ELEMENTARY_FLOW","refUnit":"m2"},"unit":{"@type":"Unit","@id":"3ce61faa-5716-41c1-aef6-b5920054acc9","name":"m2"},"flowProperty":{"@type":"FlowProperty","@id":"93a60a56-a3c8-19da-a746-0800200c9a66","name":"Area","category":"Technical flow properties","refUnit":"m2"},"uncertainty":{"@type":"Uncertainty","distributionType":"LOG_NORMAL_DISTRIBUTION","geomMean":1.0E-5,"geomSd":1.729310125349922}},{"@type":"Exchange","isAvoidedProduct":false,"isInput":false,"amount":4.0E-11,"dqEntry":"(1;1;2;1;1)","description":"Assumption by Dones, R., Bauer, C., Röder, A. (2007) Kohle. In: Dones, R. (Ed.) et al., Sachbilanzen von Energiesystemen: Grundlagen für den ökologischen Vergleich von Energiesystemen und den Einbezug von Energiesystemen in Ökobilanzen für die Schweiz. Final report ecoinvent No. 6-VI, Paul Scherrer Institut Villigen, Swiss Centre for Life Cycle Inventories, Dübendorf, CH.","internalId":8,"location":{"@type":"Location","@id":"89484b14-b36a-3d53-a942-6a3d944d2983","name":"Russia","category":"Country"},"flow":{"@type":"Flow","@id":"e11cdec3-2f12-4888-8687-920f37a95de6","name":"Arsenic ion","category":"Elementary flows/Emission to water/ground water","flowType":"ELEMENTARY_FLOW","refUnit":"kg"},"unit":{"@type":"Unit","@id":"95dd50e9-c184-4412-9afc-9764b1ffcf8f","name":"kg SWU"},"flowProperty":{"@type":"FlowProperty","@id":"93a60a56-a3c8-11da-a746-0800200b9a66","name":"Mass","category":"Technical flow properties","refUnit":"kg"},"uncertainty":{"@type":"Uncertainty","distributionType":"LOG_NORMAL_DISTRIBUTION","geomMean":4.0E-11,"geomSd":1.4139824580805163}},{"@type":"Exchange","isAvoidedProduct":false,"isInput":false,"amount":3.7037037037037E-8,"dqEntry":"(1;1;2;1;1)","description":"Calculated by default as TOC (gC) \u003d COD/2.7 (COD measured in g O2). Should more correctly be calculated from the carbon content of the specified emissions to water.","internalId":24,"location":{"@type":"Location","@id":"89484b14-b36a-3d53-a942-6a3d944d2983","name":"Russia","category":"Country"},"flow":{"@type":"Flow","@id":"73b225ab-ddc4-4a38-9ed0-ceedee987424","name":"TOC, Total Organic Carbon","category":"Elementary flows/Emission to water/ground water","flowType":"ELEMENTARY_FLOW","refUnit":"kg"},"unit":{"@type":"Unit","@id":"95dd50e9-c184-4412-9afc-9764b1ffcf8f","name":"kg SWU"},"flowProperty":{"@type":"FlowProperty","@id":"93a60a56-a3c8-11da-a746-0800200b9a66","name":"Mass","category":"Technical flow properties","refUnit":"kg"},"uncertainty":{"@type":"Uncertainty","distributionType":"LOG_NORMAL_DISTRIBUTION","geomMean":3.7037037037037E-8,"geomSd":1.729310125349922}},{"@type":"Exchange","isAvoidedProduct":false,"isInput":false,"amount":2.0E-10,"dqEntry":"(1;1;2;1;1)","description":"Assumption by Dones, R., Bauer, C., Röder, A. (2007) Kohle. In: Dones, R. (Ed.) et al., Sachbilanzen von Energiesystemen: Grundlagen für den ökologischen Vergleich von Energiesystemen und den Einbezug von Energiesystemen in Ökobilanzen für die Schweiz. Final report ecoinvent No. 6-VI, Paul Scherrer Institut Villigen, Swiss Centre for Life Cycle Inventories, Dübendorf, CH.","internalId":21,"location":{"@type":"Location","@id":"89484b14-b36a-3d53-a942-6a3d944d2983","name":"Russia","category":"Country"},"flow":{"@type":"Flow","@id":"1be475e0-ccef-4145-98e0-0d47c570a71b","name":"Selenium IV","category":"Elementary flows/Emission to water/ground water","flowType":"ELEMENTARY_FLOW","refUnit":"kg"},"unit":{"@type":"Unit","@id":"95dd50e9-c184-4412-9afc-9764b1ffcf8f","name":"kg SWU"},"flowProperty":{"@type":"FlowProperty","@id":"93a60a56-a3c8-11da-a746-0800200b9a66","name":"Mass","category":"Technical flow properties","refUnit":"kg"},"uncertainty":{"@type":"Uncertainty","distributionType":"LOG_NORMAL_DISTRIBUTION","geomMean":2.0E-10,"geomSd":1.4139824580805163}},{"@type":"Exchange","isAvoidedProduct":false,"isInput":false,"amount":1.0E-11,"dqEntry":"(1;1;2;1;1)","description":"Assumption by Dones, R., Bauer, C., Röder, A. (2007) Kohle. In: Dones, R. (Ed.) et al., Sachbilanzen von Energiesystemen: Grundlagen für den ökologischen Vergleich von Energiesystemen und den Einbezug von Energiesystemen in Ökobilanzen für die Schweiz. Final report ecoinvent No. 6-VI, Paul Scherrer Institut Villigen, Swiss Centre for Life Cycle Inventories, Dübendorf, CH.","internalId":11,"location":{"@type":"Location","@id":"89484b14-b36a-3d53-a942-6a3d944d2983","name":"Russia","category":"Country"},"flow":{"@type":"Flow","@id":"3937f5a5-b4a4-434d-9fc3-1d29064fc3f8","name":"Cadmium II","category":"Elementary flows/Emission to water/ground water","flowType":"ELEMENTARY_FLOW","refUnit":"kg"},"unit":{"@type":"Unit","@id":"95dd50e9-c184-4412-9afc-9764b1ffcf8f","name":"kg SWU"},"flowProperty":{"@type":"FlowProperty","@id":"93a60a56-a3c8-11da-a746-0800200b9a66","name":"Mass","category":"Technical flow properties","refUnit":"kg"},"uncertainty":{"@type":"Uncertainty","distributionType":"LOG_NORMAL_DISTRIBUTION","geomMean":1.0E-11,"geomSd":2.239439866122061}},{"@type":"Exchange","isAvoidedProduct":false,"isInput":true,"amount":0.02592,"dqEntry":"(1;1;2;1;1)","description":"EcoSpold01Location\u003dUCTE\nAssumption by Dones et al.: per one time of unloading from transport mode, (storing) and loading on subsequent transport mode an average demand (electric) energy of 7.2 kWh/tonne and an average land use demand of 1m2*a/tonne is required.\nReference(s):\nDones, R., Bauer, C., Röder, A. (2007) Kohle. In: Dones, R. (Ed.) et al., Sachbilanzen von Energiesystemen: Grundlagen für den ökologischen Vergleich von Energiesystemen und den Einbezug von Energiesystemen in Ökobilanzen für die Schweiz. Final report ecoinvent No. 6-VI, Paul Scherrer Institut Villigen, Swiss Centre for Life Cycle Inventories, Dübendorf, CH.","costValue":7.2E-4,"currency":{"@type":"Currency","@id":"7de74e65-ff97-404f-bf57-5d2a9134fb43","name":"Euro","refUnit":"EUR"},"internalId":2,"location":{"@type":"Location","@id":"89484b14-b36a-3d53-a942-6a3d944d2983","name":"Russia","category":"Country"},"flow":{"@type":"Flow","@id":"759b89bd-3aa6-42ad-b767-5bb9ef5d331d","name":"electricity, medium voltage","category":"D:Electricity, gas, steam and air conditioning supply/35:Electricity, gas, steam and air conditioning supply/351:Electric power generation, transmission and distribution/3510:Electric power generation, transmission and distribution","flowType":"PRODUCT_FLOW","refUnit":"MJ"},"unit":{"@type":"Unit","@id":"52765a6c-3896-43c2-b2f4-c679acf13efe","name":"MJ"},"flowProperty":{"@type":"FlowProperty","@id":"f6811440-ee37-11de-8a39-0800200c9a66","name":"Energy","category":"Technical flow properties","refUnit":"MJ"},"uncertainty":{"@type":"Uncertainty","distributionType":"LOG_NORMAL_DISTRIBUTION","geomMean":0.0072,"geomSd":1.729310125349922},"defaultProvider":{"@type":"Process","@id":"386d900c-a5ea-3731-99eb-c41d16bf71bb","name":"market for electricity, medium voltage | electricity, medium voltage | Cutoff, U","category":"D:Electricity, gas, steam and air conditioning supply/35:Electricity, gas, steam and air conditioning supply/351:Electric power generation, transmission and distribution/3510:Electric power generation, transmission and distribution","processType":"UNIT_PROCESS","flowType":"PRODUCT_FLOW","location":"RU"}},{"@type":"Exchange","isAvoidedProduct":false,"isInput":false,"amount":2.0E-7,"dqEntry":"(1;1;2;1;1)","description":"Assumption by Dones, R., Bauer, C., Röder, A. (2007) Kohle. In: Dones, R. (Ed.) et al., Sachbilanzen von Energiesystemen: Grundlagen für den ökologischen Vergleich von Energiesystemen und den Einbezug von Energiesystemen in Ökobilanzen für die Schweiz. Final report ecoinvent No. 6-VI, Paul Scherrer Institut Villigen, Swiss Centre for Life Cycle Inventories, Dübendorf, CH.","internalId":19,"location":{"@type":"Location","@id":"89484b14-b36a-3d53-a942-6a3d944d2983","name":"Russia","category":"Country"},"flow":{"@type":"Flow","@id":"44f28e11-061d-44fd-8f25-dc62a9f1fa57","name":"Manganese II","category":"Elementary flows/Emission to water/ground water","flowType":"ELEMENTARY_FLOW","refUnit":"kg"},"unit":{"@type":"Unit","@id":"95dd50e9-c184-4412-9afc-9764b1ffcf8f","name":"kg SWU"},"flowProperty":{"@type":"FlowProperty","@id":"93a60a56-a3c8-11da-a746-0800200b9a66","name":"Mass","category":"Technical flow properties","refUnit":"kg"},"uncertainty":{"@type":"Uncertainty","distributionType":"LOG_NORMAL_DISTRIBUTION","geomMean":2.0E-7,"geomSd":1.5813162494407733}},{"@type":"Exchange","isAvoidedProduct":false,"isInput":false,"amount":1.0E-5,"dqEntry":"(1;1;2;1;1)","description":"Assumption by Dones, R., Bauer, C., Röder, A. (2007) Kohle. In: Dones, R. (Ed.) et al., Sachbilanzen von Energiesystemen: Grundlagen für den ökologischen Vergleich von Energiesystemen und den Einbezug von Energiesystemen in Ökobilanzen für die Schweiz. Final report ecoinvent No. 6-VI, Paul Scherrer Institut Villigen, Swiss Centre for Life Cycle Inventories, Dübendorf, CH.","internalId":22,"location":{"@type":"Location","@id":"89484b14-b36a-3d53-a942-6a3d944d2983","name":"Russia","category":"Country"},"flow":{"@type":"Flow","@id":"ca53777e-d36e-4db0-95ce-009f1d8593b8","name":"Solids, inorganic","category":"Elementary flows/Emission to water/ground water","flowType":"ELEMENTARY_FLOW","refUnit":"kg"},"unit":{"@type":"Unit","@id":"95dd50e9-c184-4412-9afc-9764b1ffcf8f","name":"kg SWU"},"flowProperty":{"@type":"FlowProperty","@id":"93a60a56-a3c8-11da-a746-0800200b9a66","name":"Mass","category":"Technical flow properties","refUnit":"kg"},"uncertainty":{"@type":"Uncertainty","distributionType":"LOG_NORMAL_DISTRIBUTION","geomMean":1.0E-5,"geomSd":1.5813162494407733}},{"@type":"Exchange","isAvoidedProduct":false,"isInput":false,"amount":1.0E-9,"dqEntry":"(1;1;2;1;1)","description":"Assumption by Dones, R., Bauer, C., Röder, A. (2007) Kohle. In: Dones, R. (Ed.) et al., Sachbilanzen von Energiesystemen: Grundlagen für den ökologischen Vergleich von Energiesystemen und den Einbezug von Energiesystemen in Ökobilanzen für die Schweiz. Final report ecoinvent No. 6-VI, Paul Scherrer Institut Villigen, Swiss Centre for Life Cycle Inventories, Dübendorf, CH.","internalId":14,"location":{"@type":"Location","@id":"89484b14-b36a-3d53-a942-6a3d944d2983","name":"Russia","category":"Country"},"flow":{"@type":"Flow","@id":"c3b659e5-35f1-408c-8cb5-b5f9b295c76e","name":"Copper ion","category":"Elementary flows/Emission to water/ground water","flowType":"ELEMENTARY_FLOW","refUnit":"kg"},"unit":{"@type":"Unit","@id":"95dd50e9-c184-4412-9afc-9764b1ffcf8f","name":"kg SWU"},"flowProperty":{"@type":"FlowProperty","@id":"93a60a56-a3c8-11da-a746-0800200b9a66","name":"Mass","category":"Technical flow properties","refUnit":"kg"},"uncertainty":{"@type":"Uncertainty","distributionType":"LOG_NORMAL_DISTRIBUTION","geomMean":1.0E-9,"geomSd":2.239439866122061}},{"@type":"Exchange","isAvoidedProduct":false,"isInput":false,"amount":2.0E-10,"dqEntry":"(1;1;2;1;1)","description":"Assumption by Dones, R., Bauer, C., Röder, A. (2007) Kohle. In: Dones, R. (Ed.) et al., Sachbilanzen von Energiesystemen: Grundlagen für den ökologischen Vergleich von Energiesystemen und den Einbezug von Energiesystemen in Ökobilanzen für die Schweiz. Final report ecoinvent No. 6-VI, Paul Scherrer Institut Villigen, Swiss Centre for Life Cycle Inventories, Dübendorf, CH.","internalId":18,"location":{"@type":"Location","@id":"89484b14-b36a-3d53-a942-6a3d944d2983","name":"Russia","category":"Country"},"flow":{"@type":"Flow","@id":"c864aa15-0abc-41ad-9889-348106e485d8","name":"Lead II","category":"Elementary flows/Emission to water/ground water","flowType":"ELEMENTARY_FLOW","refUnit":"kg"},"unit":{"@type":"Unit","@id":"95dd50e9-c184-4412-9afc-9764b1ffcf8f","name":"kg SWU"},"flowProperty":{"@type":"FlowProperty","@id":"93a60a56-a3c8-11da-a746-0800200b9a66","name":"Mass","category":"Technical flow properties","refUnit":"kg"},"uncertainty":{"@type":"Uncertainty","distributionType":"LOG_NORMAL_DISTRIBUTION","geomMean":2.0E-10,"geomSd":2.239439866122061}},{"@type":"Exchange","isAvoidedProduct":false,"isInput":false,"amount":2.0E-10,"dqEntry":"(1;1;2;1;1)","description":"Assumption by Dones, R., Bauer, C., Röder, A. (2007) Kohle. In: Dones, R. (Ed.) et al., Sachbilanzen von Energiesystemen: Grundlagen für den ökologischen Vergleich von Energiesystemen und den Einbezug von Energiesystemen in Ökobilanzen für die Schweiz. Final report ecoinvent No. 6-VI, Paul Scherrer Institut Villigen, Swiss Centre for Life Cycle Inventories, Dübendorf, CH.","internalId":13,"location":{"@type":"Location","@id":"89484b14-b36a-3d53-a942-6a3d944d2983","name":"Russia","category":"Country"},"flow":{"@type":"Flow","@id":"e5465f7b-a0c5-3ae2-8066-14f52e4cf64d","name":"Chromium III","category":"Elementary flows/Emission to water/ground water","flowType":"ELEMENTARY_FLOW","refUnit":"kg"},"unit":{"@type":"Unit","@id":"95dd50e9-c184-4412-9afc-9764b1ffcf8f","name":"kg SWU"},"flowProperty":{"@type":"FlowProperty","@id":"93a60a56-a3c8-11da-a746-0800200b9a66","name":"Mass","category":"Technical flow properties","refUnit":"kg"},"uncertainty":{"@type":"Uncertainty","distributionType":"LOG_NORMAL_DISTRIBUTION","geomMean":2.0E-10,"geomSd":1.729310125349922}},{"@type":"Exchange","isAvoidedProduct":false,"isInput":false,"amount":1.0E-4,"dqEntry":"(1;1;2;1;1)","description":"Assumption by Dones, R., Bauer, C., Röder, A. (2007) Kohle. In: Dones, R. (Ed.) et al., Sachbilanzen von Energiesystemen: Grundlagen für den ökologischen Vergleich von Energiesystemen und den Einbezug von Energiesystemen in Ökobilanzen für die Schweiz. Final report ecoinvent No. 6-VI, Paul Scherrer Institut Villigen, Swiss Centre for Life Cycle Inventories, Dübendorf, CH.","internalId":16,"location":{"@type":"Location","@id":"89484b14-b36a-3d53-a942-6a3d944d2983","name":"Russia","category":"Country"},"flow":{"@type":"Flow","@id":"54c743a4-5438-4f3c-8e84-89b3e6ec0cc0","name":"Dissolved solids","category":"Elementary flows/Emission to water/ground water","flowType":"ELEMENTARY_FLOW","refUnit":"kg"},"unit":{"@type":"Unit","@id":"95dd50e9-c184-4412-9afc-9764b1ffcf8f","name":"kg SWU"},"flowProperty":{"@type":"FlowProperty","@id":"93a60a56-a3c8-11da-a746-0800200b9a66","name":"Mass","category":"Technical flow properties","refUnit":"kg"},"uncertainty":{"@type":"Uncertainty","distributionType":"LOG_NORMAL_DISTRIBUTION","geomMean":1.0E-4,"geomSd":1.4139824580805163}},{"@type":"Exchange","isAvoidedProduct":false,"isInput":false,"amount":2.0E-9,"dqEntry":"(1;1;2;1;1)","description":"Assumption by Dones, R., Bauer, C., Röder, A. (2007) Kohle. In: Dones, R. (Ed.) et al., Sachbilanzen von Energiesystemen: Grundlagen für den ökologischen Vergleich von Energiesystemen und den Einbezug von Energiesystemen in Ökobilanzen für die Schweiz. Final report ecoinvent No. 6-VI, Paul Scherrer Institut Villigen, Swiss Centre for Life Cycle Inventories, Dübendorf, CH.","internalId":17,"location":{"@type":"Location","@id":"89484b14-b36a-3d53-a942-6a3d944d2983","name":"Russia","category":"Country"},"flow":{"@type":"Flow","@id":"33fd8342-58e7-45c9-ad92-0951c002c403","name":"Iron ion","category":"Elementary flows/Emission to water/ground water","flowType":"ELEMENTARY_FLOW","refUnit":"kg"},"unit":{"@type":"Unit","@id":"95dd50e9-c184-4412-9afc-9764b1ffcf8f","name":"kg SWU"},"flowProperty":{"@type":"FlowProperty","@id":"93a60a56-a3c8-11da-a746-0800200b9a66","name":"Mass","category":"Technical flow properties","refUnit":"kg"},"uncertainty":{"@type":"Uncertainty","distributionType":"LOG_NORMAL_DISTRIBUTION","geomMean":2.0E-9,"geomSd":3.168493566955497}}],"socialAspects":[],"allocationFactors":[]}